[
  {
    "latitude": 4.896715896,
    "longitude": 7.099736791
  },
  {
    "latitude": 4.898282322,
    "longitude": 7.099798273
  },
  {
    "latitude": 4.899659423,
    "longitude": 7.099834299
  },
  {
    "latitude": 4.900875619,
    "longitude": 7.09984498
  },
  {
    "latitude": 4.901959335,
    "longitude": 7.099830405
  },
  {
    "latitude": 4.902938974,
    "longitude": 7.099790703
  },
  {
    "latitude": 4.90384297,
    "longitude": 7.099725964
  },
  {
    "latitude": 4.904699725,
    "longitude": 7.099636316
  },
  {
    "latitude": 4.905537665,
    "longitude": 7.099521839
  },
  {
    "latitude": 4.90637956,
    "longitude": 7.099382895
  },
  {
    "latitude": 4.907225547,
    "longitude": 7.099220725
  },
  {
    "latitude": 4.908070134,
    "longitude": 7.099036832
  },
  {
    "latitude": 4.908907809,
    "longitude": 7.098832712
  },
  {
    "latitude": 4.909733071,
    "longitude": 7.098609839
  },
  {
    "latitude": 4.910540417,
    "longitude": 7.098369717
  },
  {
    "latitude": 4.911324335,
    "longitude": 7.09811383
  },
  {
    "latitude": 4.912079325,
    "longitude": 7.097843673
  },
  {
    "latitude": 4.91280094,
    "longitude": 7.097560494
  },
  {
    "latitude": 4.913488928,
    "longitude": 7.097264526
  },
  {
    "latitude": 4.914144094,
    "longitude": 7.09695577
  },
  {
    "latitude": 4.914767252,
    "longitude": 7.09663423
  },
  {
    "latitude": 4.915359198,
    "longitude": 7.096299905
  },
  {
    "latitude": 4.915920744,
    "longitude": 7.095952792
  },
  {
    "latitude": 4.916452696,
    "longitude": 7.095592881
  },
  {
    "latitude": 4.916955858,
    "longitude": 7.095220168
  },
  {
    "latitude": 4.91743091,
    "longitude": 7.094835023
  },
  {
    "latitude": 4.917877984,
    "longitude": 7.094439229
  },
  {
    "latitude": 4.918297084,
    "longitude": 7.094034923
  },
  {
    "latitude": 4.918688218,
    "longitude": 7.093624259
  },
  {
    "latitude": 4.919051401,
    "longitude": 7.093209383
  },
  {
    "latitude": 4.919386621,
    "longitude": 7.092792441
  },
  {
    "latitude": 4.919693901,
    "longitude": 7.092375579
  },
  {
    "latitude": 4.919973249,
    "longitude": 7.091960941
  },
  {
    "latitude": 4.920225239,
    "longitude": 7.09155023
  },
  {
    "latitude": 4.920452781,
    "longitude": 7.091143338
  },
  {
    "latitude": 4.920659383,
    "longitude": 7.090739725
  },
  {
    "latitude": 4.920848524,
    "longitude": 7.090338847
  },
  {
    "latitude": 4.921023693,
    "longitude": 7.089940154
  },
  {
    "latitude": 4.921188387,
    "longitude": 7.089543096
  },
  {
    "latitude": 4.921346103,
    "longitude": 7.08914714
  },
  {
    "latitude": 4.921500321,
    "longitude": 7.088751725
  },
  {
    "latitude": 4.921654279,
    "longitude": 7.088356753
  },
  {
    "latitude": 4.921810122,
    "longitude": 7.087963929
  },
  {
    "latitude": 4.921969739,
    "longitude": 7.087575386
  },
  {
    "latitude": 4.922135008,
    "longitude": 7.087193263
  },
  {
    "latitude": 4.922307832,
    "longitude": 7.086819701
  },
  {
    "latitude": 4.92249009,
    "longitude": 7.086456848
  },
  {
    "latitude": 4.922683677,
    "longitude": 7.086106836
  },
  {
    "latitude": 4.922890463,
    "longitude": 7.085771804
  },
  {
    "latitude": 4.923111863,
    "longitude": 7.085453237
  },
  {
    "latitude": 4.923347266,
    "longitude": 7.085149909
  },
  {
    "latitude": 4.92359561,
    "longitude": 7.084859968
  },
  {
    "latitude": 4.923855813,
    "longitude": 7.084581522
  },
  {
    "latitude": 4.924126794,
    "longitude": 7.084312709
  },
  {
    "latitude": 4.924407463,
    "longitude": 7.084051638
  },
  {
    "latitude": 4.924696747,
    "longitude": 7.083796457
  },
  {
    "latitude": 4.924993574,
    "longitude": 7.083545265
  },
  {
    "latitude": 4.925297072,
    "longitude": 7.083296434
  },
  {
    "latitude": 4.925607301,
    "longitude": 7.083049188
  },
  {
    "latitude": 4.925924512,
    "longitude": 7.082802994
  },
  {
    "latitude": 4.926248986,
    "longitude": 7.082557321
  },
  {
    "latitude": 4.926580973,
    "longitude": 7.082311616
  },
  {
    "latitude": 4.926920761,
    "longitude": 7.082065357
  },
  {
    "latitude": 4.927268602,
    "longitude": 7.081818002
  },
  {
    "latitude": 4.927624765,
    "longitude": 7.081569018
  },
  {
    "latitude": 4.927989663,
    "longitude": 7.081317232
  },
  {
    "latitude": 4.928364208,
    "longitude": 7.081058982
  },
  {
    "latitude": 4.928749471,
    "longitude": 7.080789963
  },
  {
    "latitude": 4.929146509,
    "longitude": 7.080505892
  },
  {
    "latitude": 4.929556393,
    "longitude": 7.080202474
  },
  {
    "latitude": 4.929980186,
    "longitude": 7.079875396
  },
  {
    "latitude": 4.930418935,
    "longitude": 7.079520383
  },
  {
    "latitude": 4.93087372,
    "longitude": 7.079133131
  },
  {
    "latitude": 4.931345769,
    "longitude": 7.078709607
  },
  {
    "latitude": 4.931837062,
    "longitude": 7.078246866
  },
  {
    "latitude": 4.93245701,
    "longitude": 7.077632314
  },
  {
    "latitude": 4.932885892,
    "longitude": 7.077192956
  },
  {
    "latitude": 4.933447727,
    "longitude": 7.076596418
  },
  {
    "latitude": 4.934037363,
    "longitude": 7.075949893
  },
  {
    "latitude": 4.934656936,
    "longitude": 7.075250696
  },
  {
    "latitude": 4.935308598,
    "longitude": 7.074496153
  },
  {
    "latitude": 4.935993308,
    "longitude": 7.073685964
  },
  {
    "latitude": 4.93670732,
    "longitude": 7.072829505
  },
  {
    "latitude": 4.937445733,
    "longitude": 7.071938527
  },
  {
    "latitude": 4.938203635,
    "longitude": 7.071024801
  },
  {
    "latitude": 4.938976105,
    "longitude": 7.070100096
  },
  {
    "latitude": 4.939758231,
    "longitude": 7.069176181
  },
  {
    "latitude": 4.940545102,
    "longitude": 7.068264817
  },
  {
    "latitude": 4.941331808,
    "longitude": 7.067377774
  },
  {
    "latitude": 4.942115451,
    "longitude": 7.066523489
  },
  {
    "latitude": 4.94290119,
    "longitude": 7.065697053
  },
  {
    "latitude": 4.943696215,
    "longitude": 7.06489024
  },
  {
    "latitude": 4.944507719,
    "longitude": 7.064094808
  },
  {
    "latitude": 4.945342865,
    "longitude": 7.063302524
  },
  {
    "latitude": 4.946208852,
    "longitude": 7.062505154
  },
  {
    "latitude": 4.947112864,
    "longitude": 7.061694465
  },
  {
    "latitude": 4.948062073,
    "longitude": 7.060862213
  },
  {
    "latitude": 4.949058898,
    "longitude": 7.060004361
  },
  {
    "latitude": 4.950086632,
    "longitude": 7.059133587
  },
  {
    "latitude": 4.951123806,
    "longitude": 7.058266787
  },
  {
    "latitude": 4.95214896,
    "longitude": 7.057420825
  },
  {
    "latitude": 4.953140615,
    "longitude": 7.056612586
  },
  {
    "latitude": 4.954077293,
    "longitude": 7.055858949
  },
  {
    "latitude": 4.954937536,
    "longitude": 7.055176796
  },
  {
    "latitude": 4.955699865,
    "longitude": 7.054582996
  },
  {
    "latitude": 4.956349624,
    "longitude": 7.054089259
  },
  {
    "latitude": 4.956899406,
    "longitude": 7.05368655
  },
  {
    "latitude": 4.957368611,
    "longitude": 7.053360668
  },
  {
    "latitude": 4.957776636,
    "longitude": 7.053097413
  },
  {
    "latitude": 4.958142887,
    "longitude": 7.052882556
  },
  {
    "latitude": 4.958486762,
    "longitude": 7.052701913
  },
  {
    "latitude": 4.958827667,
    "longitude": 7.052541266
  },
  {
    "latitude": 4.959185008,
    "longitude": 7.052386402
  },
  {
    "latitude": 4.959573697,
    "longitude": 7.052226074
  },
  {
    "latitude": 4.959990798,
    "longitude": 7.052060794
  },
  {
    "latitude": 4.960428871,
    "longitude": 7.051894054
  },
  {
    "latitude": 4.960880493,
    "longitude": 7.051729321
  },
  {
    "latitude": 4.961338244,
    "longitude": 7.051570069
  },
  {
    "latitude": 4.961794683,
    "longitude": 7.051419773
  },
  {
    "latitude": 4.962242388,
    "longitude": 7.051281916
  },
  {
    "latitude": 4.962673929,
    "longitude": 7.051159963
  },
  {
    "latitude": 4.963083616,
    "longitude": 7.051056276
  },
  {
    "latitude": 4.963472664,
    "longitude": 7.050968751
  },
  {
    "latitude": 4.963844011,
    "longitude": 7.050894151
  },
  {
    "latitude": 4.964200604,
    "longitude": 7.050829258
  },
  {
    "latitude": 4.964545399,
    "longitude": 7.050770837
  },
  {
    "latitude": 4.964881333,
    "longitude": 7.050715651
  },
  {
    "latitude": 4.965211364,
    "longitude": 7.050660491
  },
  {
    "latitude": 4.965538419,
    "longitude": 7.050602122
  },
  {
    "latitude": 4.965865121,
    "longitude": 7.050537272
  },
  {
    "latitude": 4.966192742,
    "longitude": 7.050462483
  },
  {
    "latitude": 4.966522196,
    "longitude": 7.050374284
  },
  {
    "latitude": 4.96685442,
    "longitude": 7.050269164
  },
  {
    "latitude": 4.967190355,
    "longitude": 7.050143659
  },
  {
    "latitude": 4.967530911,
    "longitude": 7.049994249
  },
  {
    "latitude": 4.967877037,
    "longitude": 7.049817471
  },
  {
    "latitude": 4.968229644,
    "longitude": 7.049609814
  },
  {
    "latitude": 4.968592404,
    "longitude": 7.049365137
  },
  {
    "latitude": 4.968979842,
    "longitude": 7.049066648
  },
  {
    "latitude": 4.969409204,
    "longitude": 7.048694904
  },
  {
    "latitude": 4.969897766,
    "longitude": 7.048230443
  },
  {
    "latitude": 4.970462766,
    "longitude": 7.047653823
  },
  {
    "latitude": 4.971121469,
    "longitude": 7.046945591
  },
  {
    "latitude": 4.971891122,
    "longitude": 7.046086296
  },
  {
    "latitude": 4.97278899,
    "longitude": 7.045056494
  }
]